py_contract_ui/__init__.py
py_contract_ui/generate_ui.py
py_contract_ui/public/bootstrap-5.0.2.min.css
py_contract_ui/public/bootstrap-5.0.2.min.css.map
py_contract_ui/public/web3-1.7.3.min.js
py_contract_ui/public/web3-1.7.3.min.js.map
py_contract_ui/template/__init__.py
py_contract_ui/template/template.j2
py_contract_ui-0.0.3.dist-info/LICENCE
py_contract_ui-0.0.3.dist-info/METADATA
py_contract_ui-0.0.3.dist-info/WHEEL
py_contract_ui-0.0.3.dist-info/entry_points.txt
py_contract_ui-0.0.3.dist-info/top_level.txt
py_contract_ui-0.0.3.dist-info/RECORD
