Metadata-Version: 2.1
Name: py-contract-ui
Version: 0.0.3
Summary: For converting Ethereum smart contract ABIs into interactive HTML user interface.
Home-page: https://github.com/AMJADH195/py-contract-ui.git
Author: Amjad
Author-email: amjadh1996@gmail.com
Classifier: Programming Language :: Python :: 3
Classifier: License :: OSI Approved :: MIT License
Classifier: Operating System :: OS Independent
Requires-Python: >=3.11
License-File: LICENCE
Requires-Dist: uvicorn >=0.23.2
Requires-Dist: fastapi >=0.100.1
Requires-Dist: Jinja2 >=3.1.2
